addfunctool/__init__.py
addfunctool/functool.py
addfunctool-1.0.0.dist-info/METADATA
addfunctool-1.0.0.dist-info/WHEEL
addfunctool-1.0.0.dist-info/top_level.txt
addfunctool-1.0.0.dist-info/RECORD
