Metadata-Version: 2.1
Name: addfunctool
Version: 1.0.0
Summary: Add Operator
Home-page: UNKNOWN
Author: chenweikai
Author-email: 1765026991@qq.com
License: BSD License
Platform: all
